did_peer_2-0.1.1.post1.dist-info/METADATA
did_peer_2-0.1.1.post1.dist-info/WHEEL
did_peer_2/__init__.py
did_peer_2-0.1.1.post1.dist-info/RECORD
