Metadata-Version: 2.1
Name: did-peer-2
Version: 0.1.1.post1
Summary: An implementation of did:peer:2
Author-Email: Daniel Bluhm <dbluhm@pm.me>
License: Apache-2.0
Requires-Python: >=3.9
Requires-Dist: base58>=2.1.1
